{
  "apiVersions": {
    "ActionGroupsApi": "2024-10-01-preview",
    "ActivityLogAlertsApi": "2023-01-01-preview",
    "ActivityLogsApi": "2015-04-01",
    "AlertRulesIncidentsApi": "2016-03-01",
    "AutoScaleApi": "2022-10-01",
    "DataCollectionApi": "2024-03-11",
    "LogProfilesApi": "2016-03-01",
    "MetricAlertApi": "2024-03-01-preview",
    "MetricBaselinesApi": "2019-03-01",
    "MetricsApi": "2024-02-01",
    "NetworkSecurityPerimeterApi": "2021-10-01",
    "PrivateLinkScopesApi": "2023-06-01-preview",
    "ScheduledQueryRuleApi": "2025-01-01-preview",
    "ServiceDiagnosticsSettingsApi": "2016-09-01"
  },
  "commit": "84ee97f0cd82f3432f0ff0185e4deeb58624aac6",
  "repository_url": "https://github.com/Azure/azure-rest-api-specs",
  "typespec_src": "specification/monitor/resource-manager/Microsoft.Insights/Insights",
  "emitterVersion": "0.63.0"
}